rwlock/__init__.py
rwlock/rwlock.py
rwlock-0.0.5.dist-info/DESCRIPTION.rst
rwlock-0.0.5.dist-info/METADATA
rwlock-0.0.5.dist-info/RECORD
rwlock-0.0.5.dist-info/WHEEL
rwlock-0.0.5.dist-info/metadata.json
rwlock-0.0.5.dist-info/top_level.txt
